<gametext>
  
  <goals>
    <goal>Обойти все препятствия и дойти до конца</goal>
  </goals>


  <ingamedialogs>
    <ingamedialog time="7">
      <dialogs>
        <dialog nameid ="4">
          <text>Свободный полёт уменьшит мощность двигателя, но даст большую скорость без торможения.</text>
        </dialog>
      </dialogs>
    </ingamedialog>
    <ingamedialog time="7">
      <dialogs>
        <dialog nameid ="4">
          <text>Скованный полёт увеличит мощность двигателя и позволит вам легче пробраться через узкие пространства.</text>
        </dialog>
      </dialogs>
    </ingamedialog>
    <ingamedialog time="5">
      <dialogs>
        <dialog nameid ="5">
          <text>Что это за статуя?</text>
        </dialog>
        <dialog nameid ="4">
          <text>Раньше здесь был музей.</text>
        </dialog>
        <dialog nameid ="4">
          <text>Но Совет Z дал приказ уничтожить памятники.</text>
        </dialog>
        <dialog nameid ="4">
          <text>Про этот, похоже, забыли.</text>
        </dialog>
      </dialogs>
    </ingamedialog>
    <ingamedialog time="6">
      <dialogs>
        <dialog nameid ="4">
          <text>Хорошо.</text>
        </dialog>
      </dialogs>
    </ingamedialog>
  </ingamedialogs>


  <startdialogs>
    <dialog nameid ="4">
      <text>Каин, у вас огромные успехи в пилотировании, и вам дали возможность испытать себя на продвинутом уровне.</text>
    </dialog>
    <dialog nameid ="5">
      <text>Спасибо.</text>
    </dialog>
    <dialog nameid ="4">
      <text>Тексты всегда были ободряющими.</text>
    </dialog>
    <dialog nameid ="4">
      <text>На данном этапе вам предстоит пройти более сложную практику. У вас есть панель, показывающая режим полёта. Разные режимы полёта дают серьёзные преимущества в определённых ситуациях. Вы готовы?</text>
    </dialog>
    <dialog nameid ="5">
      <text>Да.</text>
    </dialog>
    <dialog nameid ="4">
      <text>Тогда начнём.</text>
    </dialog>
    
  </startdialogs>
</gametext>